<?xml version="1.0" encoding="UTF-8" standalone="yes" ?>
<UiModuleSettings xmlVersion="1.0" enabled="true" lastLoadedVersion="1.57" messagingEnabled="false">
    <VersionSettings xmlVersion="1.0" gameVersion="1.4.8" windowsVersion="" savedVariablesVersion="" />
    <Windows>
        <WindowSettings xmlVersion="1.0" name="EA_MoraleBar" sizeX="295.000000" sizeY="72.000000" movable="false" alpha="1.000000" fontAlpha="1.000000" scale="1.000000" showing="true">
            <Anchors>
                <WindowAnchor xmlVersion="1.0" point="bottomright" relativePoint="bottomright" relativeTo="Root" xOffset="-282.221924" yOffset="-0.000024" />
            </Anchors>
        </WindowSettings>
        <WindowSettings xmlVersion="1.0" name="EA_TacticsEditor" sizeX="350.000000" sizeY="50.000000" movable="false" alpha="1.000000" fontAlpha="1.000000" scale="0.644526" showing="true">
            <Anchors>
                <WindowAnchor xmlVersion="1.0" point="bottomright" relativePoint="bottomright" relativeTo="Root" xOffset="-2.749380" yOffset="0.000035" />
            </Anchors>
        </WindowSettings>
    </Windows>
</UiModuleSettings>
